servequery/__init__.py
servequery/_pydantic_compat.py
servequery/_registry.py
servequery/_version.py
servequery/errors.py
servequery/pydantic_utils.py
servequery/telemetry.py
servequery/cli/__init__.py
servequery/cli/__main__.py
servequery/cli/demo_project.py
servequery/cli/legacy_ui.py
servequery/cli/main.py
servequery/cli/report.py
servequery/cli/ui.py
servequery/cli/utils.py
servequery/core/__init__.py
servequery/core/_utils.py
servequery/core/base_types.py
servequery/core/compare.py
servequery/core/container.py
servequery/core/datasets.py
servequery/core/metric_types.py
servequery/core/preset_types.py
servequery/core/report.py
servequery/core/serialization.py
servequery/core/tests.py
servequery/core/registries/__init__.py
servequery/core/registries/bound_tests.py
servequery/core/registries/column_conditions.py
servequery/core/registries/descriptors.py
servequery/core/registries/metric_results.py
servequery/core/registries/metric_tests.py
servequery/core/registries/metrics.py
servequery/core/registries/presets.py
servequery/core/registries/prompts.py
servequery/descriptors/__init__.py
servequery/descriptors/_context_relevance.py
servequery/descriptors/_custom_descriptors.py
servequery/descriptors/_generate_descriptors.py
servequery/descriptors/_text_length.py
servequery/descriptors/generated_descriptors.py
servequery/descriptors/llm_judges.py
servequery/future/__init__.py
servequery/future/datasets.py
servequery/future/metric_types.py
servequery/future/report.py
servequery/future/descriptors/__init__.py
servequery/future/generators/__init__.py
servequery/future/metrics/__init__.py
servequery/future/presets/__init__.py
servequery/future/tests/__init__.py
servequery/generators/__init__.py
servequery/generators/column.py
servequery/legacy/__init__.py
servequery/legacy/__main__.py
servequery/legacy/_config.py
servequery/legacy/_registry.py
servequery/legacy/base_metric.py
servequery/legacy/core.py
servequery/legacy/metric_results.py
servequery-0.1.0.dist-info/licenses/LICENSE
servequery-0.1.0.dist-info/METADATA
servequery-0.1.0.dist-info/WHEEL
servequery-0.1.0.dist-info/entry_points.txt
servequery-0.1.0.dist-info/top_level.txt
servequery-0.1.0.dist-info/RECORD
