Metadata-Version: 2.4
Name: servequery
Version: 0.1.0
Summary: An open-source ML & LLM observability platform
Home-page: https://github.com/Rixy-Ai/ServeQuery
Author: Your Name
Author-email: support@servequery.com
Platform: Linux
Platform: Mac OS X
Platform: Windows
Requires-Python: >=3.8
License-File: LICENSE
Requires-Dist: plotly<6,>=5.10.0
Requires-Dist: statsmodels>=0.12.2
Requires-Dist: scikit-learn>=1.0.1
Requires-Dist: pandas[parquet]>=1.3.5
Requires-Dist: numpy>=1.22.0
Requires-Dist: nltk>=3.6.7
Requires-Dist: scipy>=1.10.0
Requires-Dist: requests>=2.32.0
Requires-Dist: PyYAML>=5.4
Requires-Dist: pydantic>=1.10.16
Requires-Dist: litestar>=2.8.3
Requires-Dist: typing-inspect>=0.9.0
Requires-Dist: uvicorn[standard]>=0.22.0
Requires-Dist: watchdog>=3.0.0
Requires-Dist: typer>=0.3
Requires-Dist: rich>=13
Requires-Dist: iterative-telemetry>=0.0.5
Requires-Dist: dynaconf>=3.2.4
Requires-Dist: certifi>=2024.7.4
Requires-Dist: urllib3>=1.26.19
Requires-Dist: fsspec>=2024.6.1
Requires-Dist: ujson>=5.4.0
Requires-Dist: deprecation>=2.1.0
Requires-Dist: uuid6>=2024.7.10
Requires-Dist: cryptography>=43.0.1
Provides-Extra: dev
Requires-Dist: pip-audit>=2.7.2; extra == "dev"
Requires-Dist: wheel==0.38.1; extra == "dev"
Requires-Dist: setuptools==65.5.1; python_version < "3.12" and extra == "dev"
Requires-Dist: setuptools==68.2.2; python_version >= "3.12" and extra == "dev"
Requires-Dist: jupyter==1.0.0; extra == "dev"
Requires-Dist: mypy==1.1.1; extra == "dev"
Requires-Dist: pandas-stubs>=1.3.5; extra == "dev"
Requires-Dist: pytest==7.4.4; extra == "dev"
Requires-Dist: types-PyYAML==6.0.1; extra == "dev"
Requires-Dist: types-requests==2.26.0; extra == "dev"
Requires-Dist: types-dataclasses==0.6; extra == "dev"
Requires-Dist: types-python-dateutil==2.8.19; extra == "dev"
Requires-Dist: types-ujson>=5.4.0; extra == "dev"
Requires-Dist: pillow>=10.3.0; extra == "dev"
Requires-Dist: httpx==0.27.0; extra == "dev"
Requires-Dist: ruff==0.3.7; extra == "dev"
Requires-Dist: pre-commit==3.5.0; extra == "dev"
Requires-Dist: pytest-asyncio==0.23.7; extra == "dev"
Requires-Dist: pytest-mock==3.14.0; extra == "dev"
Provides-Extra: llm
Requires-Dist: openai>=1.16.2; extra == "llm"
Requires-Dist: evaluate>=0.4.1; extra == "llm"
Requires-Dist: transformers[torch]>=4.39.3; extra == "llm"
Requires-Dist: sentence-transformers>=2.7.0; extra == "llm"
Requires-Dist: sqlvalidator>=0.0.20; extra == "llm"
Requires-Dist: litellm>=1.60.4; extra == "llm"
Provides-Extra: spark
Requires-Dist: pyspark<4,>=3.4.0; extra == "spark"
Provides-Extra: fsspec
Requires-Dist: s3fs>=2024.9.0; extra == "fsspec"
Requires-Dist: gcsfs>=2024.9.0; extra == "fsspec"
Dynamic: author
Dynamic: author-email
Dynamic: description
Dynamic: description-content-type
Dynamic: license-file
Dynamic: provides-extra
Dynamic: requires-dist
Dynamic: summary
